README.rst
setup.py
socksonsocks/__init__.py
socksonsocks.egg-info/PKG-INFO
socksonsocks.egg-info/SOURCES.txt
socksonsocks.egg-info/dependency_links.txt
socksonsocks.egg-info/top_level.txt