Metadata-Version: 1.0
Name: socksonsocks
Version: 0.2
Summary: A tool to set a socket up for using a SOCKS proxy
Home-page: https://github.com/rpicard/socksonsocks
Author: Robert Picard
Author-email: robert@robert.io
License: MIT
Platform: UNKNOWN
